pydantic_discriminated/__init__.py
pydantic_discriminated/api.py
pydantic_discriminated-0.1.28.dist-info/METADATA
pydantic_discriminated-0.1.28.dist-info/WHEEL
pydantic_discriminated-0.1.28.dist-info/licenses/LICENSE
pydantic_discriminated-0.1.28.dist-info/RECORD
