Metadata-Version: 2.4
Name: pydantic-discriminated
Version: 0.1.28
Summary: Type-safe discriminated unions for Pydantic models
Project-URL: Homepage, https://github.com/talbotknighton/pydantic-discriminated
Project-URL: Bug Tracker, https://github.com/talbotknighton/pydantic-discriminated/issues
Project-URL: Documentation, https://talbotknighton.github.io/pydantic-discriminated/
Project-URL: Source Code, https://github.com/talbotknighton/pydantic-discriminated
Project-URL: PyPI, https://pypi.org/project/pydantic-discriminated/
Author-email: Talbot Knighton <talbotknighton@gmail.com>
Maintainer-email: Talbot Knighton <talbotknighton@gmail.com>
License: MIT
License-File: LICENSE
Keywords: discriminated,polymorphic,pydantic,serialization,unions,validation
Classifier: Development Status :: 4 - Beta
Classifier: Intended Audience :: Developers
Classifier: License :: OSI Approved :: MIT License
Classifier: Operating System :: OS Independent
Classifier: Programming Language :: Python :: 3
Classifier: Programming Language :: Python :: 3.8
Classifier: Programming Language :: Python :: 3.9
Classifier: Programming Language :: Python :: 3.10
Classifier: Programming Language :: Python :: 3.11
Classifier: Programming Language :: Python :: 3.12
Classifier: Topic :: Software Development :: Libraries :: Python Modules
Classifier: Typing :: Typed
Requires-Python: >=3.8
Requires-Dist: pydantic>=2.0.0
Provides-Extra: dev
Requires-Dist: black>=23.3.0; extra == 'dev'
Requires-Dist: flake8>=6.0.0; extra == 'dev'
Requires-Dist: hatchling>=1.11.0; extra == 'dev'
Requires-Dist: isort>=5.12.0; extra == 'dev'
Requires-Dist: mike; extra == 'dev'
Requires-Dist: mkdocs-gen-files>=0.3.0; extra == 'dev'
Requires-Dist: mkdocs-literate-nav>=0.6.0; extra == 'dev'
Requires-Dist: mkdocs-material-extensions>=1.0.0; extra == 'dev'
Requires-Dist: mkdocs-material>=9.2.0; extra == 'dev'
Requires-Dist: mkdocs-redirects>=1.0.0; extra == 'dev'
Requires-Dist: mkdocs-section-index>=0.2.0; extra == 'dev'
Requires-Dist: mkdocs>=1.4.2; extra == 'dev'
Requires-Dist: mkdocstrings[python]>=0.20.0; extra == 'dev'
Requires-Dist: mypy>=1.3.0; extra == 'dev'
Requires-Dist: numpy; extra == 'dev'
Requires-Dist: numpydantic; extra == 'dev'
Requires-Dist: pandas; extra == 'dev'
Requires-Dist: pytest-cov>=4.1.0; extra == 'dev'
Requires-Dist: pytest>=7.3.1; extra == 'dev'
